<model>
	<voxels>
		<voxel a="1.0" b="0.0431" g="0.0431" r="0.0549" x="-5" y="3" z="0" />
		<voxel a="1.0" b="0.0431" g="0.0431" r="0.0549" x="-6" y="3" z="0" />
		<voxel a="1.0" b="0.0431" g="0.0431" r="0.0549" x="-7" y="3" z="0" />
		<voxel a="1.0" b="0.0549" g="0.0549" r="0.0667" x="-5" y="4" z="0" />
		<voxel a="1.0" b="0.0549" g="0.0549" r="0.0667" x="-6" y="4" z="0" />
		<voxel a="1.0" b="0.0549" g="0.0549" r="0.0667" x="-7" y="4" z="0" />
		<voxel a="1.0" b="0.1098" g="0.1098" r="0.1098" x="-8" y="4" z="0" />
		<voxel a="1.0" b="0.0667" g="0.1647" r="0.2588" x="-4" y="2" z="0" />
		<voxel a="1.0" b="0.0745" g="0.0863" r="0.098" x="-4" y="3" z="0" />
		<voxel a="1.0" b="0.0549" g="0.0549" r="0.0667" x="-4" y="4" z="0" />
		<voxel a="1.0" b="0.0667" g="0.1725" r="0.3059" x="-3" y="1" z="0" />
		<voxel a="1.0" b="0.0667" g="0.1647" r="0.2588" x="-3" y="2" z="0" />
		<voxel a="1.0" b="0.0745" g="0.0863" r="0.098" x="-3" y="3" z="0" />
		<voxel a="1.0" b="0.0549" g="0.0549" r="0.0667" x="-3" y="4" z="0" />
		<voxel a="1.0" b="0.0745" g="0.0863" r="0.098" x="-8" y="3" z="0" />
		<voxel a="1.0" b="0.0667" g="0.1647" r="0.2588" x="-4" y="2" z="-1" />
		<voxel a="1.0" b="0.0667" g="0.1725" r="0.3059" x="-3" y="1" z="-1" />
		<voxel a="1.0" b="0.0667" g="0.1647" r="0.2588" x="-3" y="2" z="-1" />
		<voxel a="1.0" b="0.0745" g="0.0863" r="0.098" x="-3" y="3" z="-1" />
		<voxel a="1.0" b="0.0549" g="0.0549" r="0.0667" x="-3" y="4" z="-1" />
		<voxel a="1.0" b="0.0549" g="0.0549" r="0.0667" x="-4" y="4" z="-1" />
		<voxel a="1.0" b="0.0745" g="0.0863" r="0.098" x="-4" y="3" z="-1" />
		<voxel a="1.0" b="0.0431" g="0.0431" r="0.0549" x="-5" y="3" z="-1" />
		<voxel a="1.0" b="0.0549" g="0.0549" r="0.0667" x="-5" y="4" z="-1" />
		<voxel a="1.0" b="0.0549" g="0.0549" r="0.0667" x="-6" y="4" z="-1" />
		<voxel a="1.0" b="0.0431" g="0.0431" r="0.0549" x="-6" y="3" z="-1" />
		<voxel a="1.0" b="0.0431" g="0.0431" r="0.0549" x="-7" y="3" z="-1" />
		<voxel a="1.0" b="0.0549" g="0.0549" r="0.0667" x="-7" y="4" z="-1" />
		<voxel a="1.0" b="0.1098" g="0.1098" r="0.1098" x="-8" y="4" z="-1" />
		<voxel a="1.0" b="0.0745" g="0.0863" r="0.098" x="-8" y="3" z="-1" />
		<voxel a="1.0" b="0.0667" g="0.1725" r="0.3059" x="-2" y="1" z="0" />
		<voxel a="1.0" b="0.0667" g="0.1725" r="0.3059" x="-2" y="1" z="-1" />
		<voxel a="1.0" b="0.0667" g="0.1725" r="0.3059" x="-2" y="0" z="0" />
		<voxel a="1.0" b="0.0667" g="0.1725" r="0.3059" x="-2" y="0" z="-1" />
		<voxel a="1.0" b="0.0667" g="0.1725" r="0.3059" x="-3" y="0" z="0" />
		<voxel a="1.0" b="0.0667" g="0.1725" r="0.3059" x="-3" y="0" z="-1" />
		<voxel a="1.0" b="0.0549" g="0.0549" r="0.0667" x="-2" y="3" z="-1" />
		<voxel a="1.0" b="0.0549" g="0.0549" r="0.0667" x="-2" y="3" z="0" />
		<voxel a="1.0" b="0.0431" g="0.0431" r="0.0549" x="-9" y="3" z="-1" />
		<voxel a="1.0" b="0.0549" g="0.0549" r="0.0667" x="-9" y="4" z="-1" />
		<voxel a="1.0" b="0.0431" g="0.0431" r="0.0549" x="-9" y="3" z="0" />
		<voxel a="1.0" b="0.0549" g="0.0549" r="0.0667" x="-9" y="4" z="0" />
		<voxel a="1.0" b="0.0667" g="0.1647" r="0.2588" x="-4" y="1" z="0" />
		<voxel a="1.0" b="0.0667" g="0.1647" r="0.2588" x="-4" y="1" z="-1" />
		<voxel a="1.0" b="0.0549" g="0.0549" r="0.0667" x="-10" y="4" z="-1" />
		<voxel a="1.0" b="0.0431" g="0.0431" r="0.0549" x="-10" y="3" z="-1" />
		<voxel a="1.0" b="0.0549" g="0.0549" r="0.0667" x="-10" y="4" z="0" />
		<voxel a="1.0" b="0.0431" g="0.0431" r="0.0549" x="-10" y="3" z="0" />
		<voxel a="1.0" b="0.0431" g="0.0431" r="0.0549" x="-11" y="3" z="-1" />
		<voxel a="1.0" b="0.0549" g="0.0549" r="0.0667" x="-11" y="4" z="-1" />
		<voxel a="1.0" b="0.0549" g="0.0549" r="0.0667" x="-11" y="4" z="0" />
		<voxel a="1.0" b="0.0431" g="0.0431" r="0.0549" x="-11" y="3" z="0" />
		<voxel a="1.0" b="0.0745" g="0.0863" r="0.098" x="-12" y="3" z="-1" />
		<voxel a="1.0" b="0.0745" g="0.0863" r="0.098" x="-12" y="4" z="-1" />
		<voxel a="1.0" b="0.0745" g="0.0863" r="0.098" x="-12" y="4" z="0" />
		<voxel a="1.0" b="0.0549" g="0.0549" r="0.0667" x="-13" y="4" z="0" />
		<voxel a="1.0" b="0.0549" g="0.0549" r="0.0667" x="-13" y="4" z="-1" />
		<voxel a="1.0" b="0.0549" g="0.0549" r="0.0667" x="-14" y="4" z="-1" />
		<voxel a="1.0" b="0.0745" g="0.0863" r="0.098" x="-12" y="3" z="0" />
		<voxel a="1.0" b="0.0431" g="0.0431" r="0.0549" x="-13" y="3" z="-1" />
		<voxel a="1.0" b="0.0431" g="0.0431" r="0.0549" x="-13" y="3" z="0" />
		<voxel a="1.0" b="0.0549" g="0.0549" r="0.0667" x="-14" y="4" z="0" />
		<voxel a="1.0" b="0.0431" g="0.0431" r="0.0549" x="-14" y="3" z="-1" />
		<voxel a="1.0" b="0.0431" g="0.0431" r="0.0549" x="-14" y="3" z="0" />
		<voxel a="1.0" b="0.0549" g="0.0549" r="0.0667" x="-15" y="4" z="-1" />
		<voxel a="1.0" b="0.0549" g="0.0549" r="0.0667" x="-15" y="4" z="0" />
		<voxel a="1.0" b="0.0431" g="0.0431" r="0.0549" x="-15" y="3" z="-1" />
		<voxel a="1.0" b="0.0431" g="0.0431" r="0.0549" x="-15" y="3" z="0" />
	</voxels>
	<skeleton />
	<skeletonVoxelBindings />
</model>